plastron/cli/__init__.py
plastron/cli/commands/__init__.py
plastron/cli/commands/annotate.py
plastron/cli/commands/create.py
plastron/cli/commands/delete.py
plastron/cli/commands/echo.py
plastron/cli/commands/export.py
plastron/cli/commands/extractocr.py
plastron/cli/commands/find.py
plastron/cli/commands/imgsize.py
plastron/cli/commands/importcommand.py
plastron/cli/commands/list.py
plastron/cli/commands/load.py
plastron/cli/commands/ping.py
plastron/cli/commands/publish.py
plastron/cli/commands/reindex.py
plastron/cli/commands/set.py
plastron/cli/commands/stub.py
plastron/cli/commands/unpublish.py
plastron/cli/commands/update.py
plastron/cli/commands/verify.py
plastron/cli/handlers/__init__.py
plastron/cli/handlers/mapped-csv.py
plastron/cli/handlers/reel.py
plastron/cli/handlers/turtle.py
plastron_cli-4.6.2.dist-info/METADATA
plastron_cli-4.6.2.dist-info/WHEEL
plastron_cli-4.6.2.dist-info/entry_points.txt
plastron_cli-4.6.2.dist-info/top_level.txt
plastron_cli-4.6.2.dist-info/RECORD
