Metadata-Version: 2.4
Name: plastron-cli
Version: 4.6.2
Summary: Plastron command line client
Author-email: University of Maryland Libraries <lib-ssdr@umd.edu>, Josh Westgard <westgard@umd.edu>, Peter Eichman <peichman@umd.edu>, Mohamed Abdul Rasheed <mohideen@umd.edu>, Ben Wallberg <wallberg@umd.edu>, David Steelman <dsteelma@umd.edu>, Marc Andreu Grillo Aguilar <aguilarm@umd.edu>
Requires-Python: >=3.10
Requires-Dist: BeautifulSoup4
Requires-Dist: lxml<6.0
Requires-Dist: Pillow
Requires-Dist: plastron-jobs
Requires-Dist: plastron-models
Requires-Dist: plastron-repo
Requires-Dist: plastron-utils
Requires-Dist: pyparsing
Requires-Dist: pysolr
Requires-Dist: PyYAML
Requires-Dist: rdflib
Provides-Extra: test
Requires-Dist: pytest; extra == "test"
Requires-Dist: pytest-cov; extra == "test"
